misc/notebooks/report.ipynb
rainbow/__init__.py
rainbow/__main__.py
rainbow/data_analysis.py
rainbow/file_processing.py
rainbow/util.py
rainbow/optical_flow/__init__.py
rainbow/optical_flow/base_model.py
rainbow/optical_flow/gma.py
rainbow/optical_flow/model_factory.py
rainbow/optical_flow/optical_flow.py
rainbow/optical_flow/third_party/gma/core/corr.py
rainbow/optical_flow/third_party/gma/core/datasets.py
rainbow/optical_flow/third_party/gma/core/extractor.py
rainbow/optical_flow/third_party/gma/core/gma.py
rainbow/optical_flow/third_party/gma/core/network.py
rainbow/optical_flow/third_party/gma/core/update.py
rainbow/optical_flow/third_party/gma/core/__pycache__/corr.cpython-37.pyc
rainbow/optical_flow/third_party/gma/core/__pycache__/corr.cpython-38.pyc
rainbow/optical_flow/third_party/gma/core/__pycache__/corr.cpython-39.pyc
rainbow/optical_flow/third_party/gma/core/__pycache__/extractor.cpython-37.pyc
rainbow/optical_flow/third_party/gma/core/__pycache__/extractor.cpython-38.pyc
rainbow/optical_flow/third_party/gma/core/__pycache__/extractor.cpython-39.pyc
rainbow/optical_flow/third_party/gma/core/__pycache__/gma.cpython-37.pyc
rainbow/optical_flow/third_party/gma/core/__pycache__/gma.cpython-38.pyc
rainbow/optical_flow/third_party/gma/core/__pycache__/gma.cpython-39.pyc
rainbow/optical_flow/third_party/gma/core/__pycache__/network.cpython-37.pyc
rainbow/optical_flow/third_party/gma/core/__pycache__/network.cpython-38.pyc
rainbow/optical_flow/third_party/gma/core/__pycache__/network.cpython-39.pyc
rainbow/optical_flow/third_party/gma/core/__pycache__/update.cpython-37.pyc
rainbow/optical_flow/third_party/gma/core/__pycache__/update.cpython-38.pyc
rainbow/optical_flow/third_party/gma/core/__pycache__/update.cpython-39.pyc
rainbow/optical_flow/third_party/gma/core/utils/__init__.py
rainbow/optical_flow/third_party/gma/core/utils/augmentor.py
rainbow/optical_flow/third_party/gma/core/utils/flow_viz.py
rainbow_optical_flow-2022.4.6.dist-info/LICENSE
rainbow_optical_flow-2022.4.6.dist-info/METADATA
rainbow_optical_flow-2022.4.6.dist-info/WHEEL
rainbow_optical_flow-2022.4.6.dist-info/entry_points.txt
rainbow_optical_flow-2022.4.6.dist-info/top_level.txt
rainbow_optical_flow-2022.4.6.dist-info/RECORD
