Metadata-Version: 2.1
Name: rainbow-optical-flow
Version: 2022.4.6
Summary: Automated air liquid interface cell culture analysis using deep optical flow.
Home-page: https://github.com/AlphonsG/Rainbow-Optical-Flow-For-ALI
Author: Alphons Gwatimba
Author-email: 0go0vdp95@mozmail.com
License: MIT
Platform: UNKNOWN
Classifier: License :: OSI Approved :: MIT License
Classifier: Programming Language :: Python :: 3
Classifier: Programming Language :: Python :: 3.8
Classifier: Operating System :: OS Independent
Classifier: Operating System :: Microsoft :: Windows
Classifier: Operating System :: MacOS
Classifier: Operating System :: POSIX :: Linux
Classifier: Development Status :: 5 - Production/Stable
Classifier: Intended Audience :: Developers
Classifier: Intended Audience :: End Users/Desktop
Classifier: Intended Audience :: Science/Research
Classifier: Natural Language :: English
Classifier: Topic :: Scientific/Engineering
Classifier: Topic :: Scientific/Engineering :: Artificial Intelligence
Classifier: Topic :: Scientific/Engineering :: Bio-Informatics
Classifier: Topic :: Scientific/Engineering :: Image Processing
Classifier: Topic :: Scientific/Engineering :: Visualization
Requires-Python: >=3.8
License-File: LICENSE
Requires-Dist: moviepy
Requires-Dist: matplotlib
Requires-Dist: natsort
Requires-Dist: opencv-python
Requires-Dist: pandas
Requires-Dist: PIMS
Requires-Dist: nd2reader
Requires-Dist: PyYAML
Requires-Dist: scikit-image
Requires-Dist: tqdm
Requires-Dist: ipympl
Requires-Dist: einops
Requires-Dist: pytest
Requires-Dist: Gooey
Requires-Dist: imutils
Requires-Dist: astropy
Requires-Dist: jupyterlab
Requires-Dist: physt
Requires-Dist: bumpver
Requires-Dist: Pillow (<9.1.0) ; platform_system == "Darwin"
